README.md
setup.cfg
setup.py
baseapp_e2e/__init__.py
baseapp_e2e/conf.py
baseapp_e2e/utils.py
baseapp_e2e/wsgi.py
baseapp_e2e.egg-info/PKG-INFO
baseapp_e2e.egg-info/SOURCES.txt
baseapp_e2e.egg-info/dependency_links.txt
baseapp_e2e.egg-info/requires.txt
baseapp_e2e.egg-info/top_level.txt
baseapp_e2e/e2e_scripts/__init__.py
baseapp_e2e/e2e_scripts/demo.py
baseapp_e2e/rest_framework/__init__.py
baseapp_e2e/rest_framework/permissions.py
baseapp_e2e/rest_framework/serializers.py
baseapp_e2e/rest_framework/views.py
baseapp_e2e/tests/__init__.py
baseapp_e2e/tests/conftest.py
baseapp_e2e/tests/factories.py
baseapp_e2e/tests/fixtures.py
baseapp_e2e/tests/helpers.py
baseapp_e2e/tests/mixins.py
baseapp_e2e/tests/integration/__init__.py
baseapp_e2e/tests/integration/test_migration_health_check.py
baseapp_e2e/tests/integration/api/__init__.py
baseapp_e2e/tests/integration/api/test_e2e_endpoints.py
testproject/__init__.py
testproject/factories.py
testproject/settings.py
testproject/urls.py
testproject/wsgi.py
testproject/e2e/__init__.py
testproject/e2e/scripts/__init__.py
testproject/e2e/scripts/hello.py
testproject/e2e/scripts/world.py
testproject/testapp/__init__.py
testproject/testapp/admin.py
testproject/testapp/models.py
testproject/testapp/migrations/0001_initial.py
testproject/testapp/migrations/0002_auto_20230925_2201.py
testproject/testapp/migrations/__init__.py