Metadata-Version: 2.1
Name: baseapp-e2e
Version: 0.2
Summary: BaseApp End-To-End Tests
Home-page: https://github.com/silverlogic/baseapp-backend
Author: The SilverLogic
Author-email: dev@tsl.io
License: BSD-3-Clause  # Example license
Platform: UNKNOWN
Requires-Python: >=3.8
